[
    { "name": "John", "game": "Fortnite", "price": "10" },
    { "name": "Sarah", "game": "Minecraft", "price": "15" },
    { "name": "Mike", "game": "Call of Duty", "price": "12" },
    { "name": "Emily", "game": "Overwatch", "price": "10" },
    { "name": "David", "game": "Fortnite", "price": "15" },
    { "name": "Kate", "game": "Minecraft", "price": "12" },
    { "name": "Tom", "game": "Call of Duty", "price": "18" },
    { "name": "Cynthia", "game": "Overwatch", "price": "8" },
    { "name": "Josh", "game": "Fortnite", "price": "20" },
    { "name": "Nicole", "game": "Minecraft", "price": "10" },
    { "name": "Ben", "game": "Call of Duty", "price": "15" },
    { "name": "Nancy", "game": "Overwatch", "price": "12" },
    { "name": "Jack", "game": "Fortnite", "price": "12" },
    { "name": "Jessica", "game": "Minecraft", "price": "18" },
    { "name": "Brandon", "game": "Call of Duty", "price": "20" }
  ]
  